[
  {
    "id": "1776339980087-XRPUSDT",
    "symbol": "XRPUSDT",
    "outcome": "WIN",
    "regime": "TRENDING",
    "btcRisk": "GREEN",
    "score": 81,
    "sector": "BLUE_CHIP",
    "module": "VWAP_PULLBACK",
    "entryArchetype": "Institutional VWAP Reclaim",
    "liquidityTier": "HIGH",
    "scoreBeforeMomentum": 81,
    "momentumAdjustment": 0,
    "requiredScore": 68,
    "requiredStrongCategories": null,
    "expectedHoldingHours": 12,
    "riskModel": {
      "tpMultiplier": 3,
      "slMultiplier": 1.4,
      "realRR": 2.14,
      "timeStopHours": 12
    },
    "hoursOpen": 1.8,
    "favorableMovePct": 1.31,
    "adverseMovePct": 0,
    "mfePct": 1.31,
    "maePct": 0,
    "entryMetrics": {
      "distToEma9": -0.09,
      "distToEma21": -0.1,
      "distToEma50": 0.24,
      "atrPercent": 0.39,
      "bbPercent": 0.36,
      "breakoutDistancePct": -1.1,
      "pullbackFromHigh20Pct": 1.1,
      "riskRewardRatio": 2.14,
      "timeStopHours": 12
    },
    "qualityBreakdown": {
      "trend": 94.9,
      "expansion": 0,
      "participation": 62.6,
      "execution": 88
    },
    "relativeStrengthSnapshot": {
      "rs1h": 0.0116,
      "rs4h": 0.0222,
      "rs24h": 0.03
    },
    "volumeLiquidityConfirmation": {
      "minVolumeRatio": 1.1,
      "volumeRatio": 1.13,
      "volumePass": true,
      "deltaRatio": null,
      "deltaPass": null,
      "obi": 0.123,
      "obiPass": true,
      "spreadBps": 0.7,
      "depthQuoteTopN": 777472,
      "liquidityTier": "HIGH"
    },
    "rejectReasonCode": null,
    "volumeRatio": 1.13,
    "closedAt": 1776346319404
  },
  {
    "id": "1776341754394-LTCUSDT",
    "symbol": "LTCUSDT",
    "outcome": "LOSS",
    "regime": "TRENDING",
    "btcRisk": "GREEN",
    "score": 78,
    "sector": "OTHER",
    "module": "VWAP_PULLBACK",
    "entryArchetype": "Institutional VWAP Reclaim",
    "liquidityTier": "LOW",
    "scoreBeforeMomentum": 78,
    "momentumAdjustment": 0,
    "requiredScore": 68,
    "requiredStrongCategories": null,
    "expectedHoldingHours": 12,
    "riskModel": {
      "tpMultiplier": 3,
      "slMultiplier": 1.4,
      "realRR": 2.14,
      "timeStopHours": 12
    },
    "hoursOpen": 1.8,
    "favorableMovePct": 0.45,
    "adverseMovePct": 0.81,
    "mfePct": 0.45,
    "maePct": 0.81,
    "entryMetrics": {
      "distToEma9": 0.27,
      "distToEma21": 0.21,
      "distToEma50": 0.31,
      "atrPercent": 0.3,
      "bbPercent": 0.64,
      "breakoutDistancePct": -0.36,
      "pullbackFromHigh20Pct": 0.36,
      "riskRewardRatio": 2.14,
      "timeStopHours": 12
    },
    "qualityBreakdown": {
      "trend": 81.3,
      "expansion": 0,
      "participation": 80.4,
      "execution": 66
    },
    "relativeStrengthSnapshot": {
      "rs1h": 0.001,
      "rs4h": 0.0202,
      "rs24h": 0.01
    },
    "volumeLiquidityConfirmation": {
      "minVolumeRatio": 1.1,
      "volumeRatio": 2.02,
      "volumePass": true,
      "deltaRatio": null,
      "deltaPass": null,
      "obi": -0.024,
      "obiPass": true,
      "spreadBps": 1.8,
      "depthQuoteTopN": 651894,
      "liquidityTier": "LOW"
    },
    "rejectReasonCode": null,
    "volumeRatio": 2.02,
    "closedAt": 1776348177447
  },
  {
    "id": "1776339980515-DOGEUSDT",
    "symbol": "DOGEUSDT",
    "outcome": "LOSS",
    "regime": "TRENDING",
    "btcRisk": "GREEN",
    "score": 78,
    "sector": "MEME",
    "module": "VWAP_PULLBACK",
    "entryArchetype": "Institutional VWAP Reclaim",
    "liquidityTier": "MEDIUM",
    "scoreBeforeMomentum": 78,
    "momentumAdjustment": 0,
    "requiredScore": 71,
    "requiredStrongCategories": null,
    "expectedHoldingHours": 12,
    "riskModel": {
      "tpMultiplier": 2.85,
      "slMultiplier": 1.33,
      "realRR": 2.14,
      "timeStopHours": 12
    },
    "hoursOpen": 2.5,
    "favorableMovePct": 1.13,
    "adverseMovePct": 0.77,
    "mfePct": 1.13,
    "maePct": 0.77,
    "entryMetrics": {
      "distToEma9": 0.23,
      "distToEma21": 0.13,
      "distToEma50": 0.29,
      "atrPercent": 0.43,
      "bbPercent": 0.53,
      "breakoutDistancePct": -0.78,
      "pullbackFromHigh20Pct": 0.78,
      "riskRewardRatio": 2.14,
      "timeStopHours": 12
    },
    "qualityBreakdown": {
      "trend": 79.1,
      "expansion": 0,
      "participation": 80.6,
      "execution": 71
    },
    "relativeStrengthSnapshot": {
      "rs1h": 0.0014,
      "rs4h": 0.0184,
      "rs24h": 0.02
    },
    "volumeLiquidityConfirmation": {
      "minVolumeRatio": 1.1,
      "volumeRatio": 2.03,
      "volumePass": true,
      "deltaRatio": null,
      "deltaPass": null,
      "obi": 0.039,
      "obiPass": true,
      "spreadBps": 2.1,
      "depthQuoteTopN": 1363663,
      "liquidityTier": "MEDIUM"
    },
    "rejectReasonCode": null,
    "volumeRatio": 2.03,
    "closedAt": 1776348953442
  },
  {
    "id": "1776347149765-TRXUSDT",
    "symbol": "TRXUSDT",
    "outcome": "LOSS",
    "regime": "HIGH_VOL_BREAKOUT",
    "btcRisk": "GREEN",
    "score": 75,
    "sector": "OTHER",
    "module": "VWAP_PULLBACK",
    "entryArchetype": "Institutional VWAP Reclaim",
    "liquidityTier": "LOW",
    "scoreBeforeMomentum": 75,
    "momentumAdjustment": 0,
    "requiredScore": 68,
    "requiredStrongCategories": null,
    "expectedHoldingHours": 12,
    "riskModel": {
      "tpMultiplier": 3,
      "slMultiplier": 1.4,
      "realRR": 2.14,
      "timeStopHours": 12
    },
    "hoursOpen": 1.8,
    "favorableMovePct": 0,
    "adverseMovePct": 0.21,
    "mfePct": 0,
    "maePct": 0.21,
    "entryMetrics": {
      "distToEma9": 0.1,
      "distToEma21": 0.15,
      "distToEma50": 0.22,
      "atrPercent": 0.12,
      "bbPercent": 0.74,
      "breakoutDistancePct": -0.12,
      "pullbackFromHigh20Pct": 0.12,
      "riskRewardRatio": 2.14,
      "timeStopHours": 12
    },
    "qualityBreakdown": {
      "trend": 93.1,
      "expansion": 0,
      "participation": 63.4,
      "execution": 63
    },
    "relativeStrengthSnapshot": {
      "rs1h": 0.0035,
      "rs4h": 0.0264,
      "rs24h": -0.01
    },
    "volumeLiquidityConfirmation": {
      "minVolumeRatio": 1.1,
      "volumeRatio": 1.17,
      "volumePass": true,
      "deltaRatio": null,
      "deltaPass": null,
      "obi": 0.24,
      "obiPass": true,
      "spreadBps": 3.1,
      "depthQuoteTopN": 2939148,
      "liquidityTier": "LOW"
    },
    "rejectReasonCode": null,
    "volumeRatio": 1.17,
    "closedAt": 1776353519678
  },
  {
    "id": "1776349914747-FILUSDT",
    "symbol": "FILUSDT",
    "outcome": "WIN",
    "regime": "HIGH_VOL_BREAKOUT",
    "btcRisk": "GREEN",
    "score": 79,
    "sector": "OTHER",
    "module": "VWAP_PULLBACK",
    "entryArchetype": "Institutional VWAP Reclaim",
    "liquidityTier": "LOW",
    "scoreBeforeMomentum": 79,
    "momentumAdjustment": 0,
    "requiredScore": 68,
    "requiredStrongCategories": null,
    "expectedHoldingHours": 12,
    "riskModel": {
      "tpMultiplier": 3,
      "slMultiplier": 1.4,
      "realRR": 2.14,
      "timeStopHours": 12
    },
    "hoursOpen": 1.2,
    "favorableMovePct": 3.78,
    "adverseMovePct": 0,
    "mfePct": 3.78,
    "maePct": 0,
    "entryMetrics": {
      "distToEma9": -1.18,
      "distToEma21": -0.8,
      "distToEma50": 0.66,
      "atrPercent": 1.09,
      "bbPercent": 0.37,
      "breakoutDistancePct": -3.1,
      "pullbackFromHigh20Pct": 3.1,
      "riskRewardRatio": 2.14,
      "timeStopHours": 12
    },
    "qualityBreakdown": {
      "trend": 100,
      "expansion": 0,
      "participation": 67.9,
      "execution": 58
    },
    "relativeStrengthSnapshot": {
      "rs1h": 0.0292,
      "rs4h": 0.1066,
      "rs24h": 0.09
    },
    "volumeLiquidityConfirmation": {
      "minVolumeRatio": 1.1,
      "volumeRatio": 1.39,
      "volumePass": true,
      "deltaRatio": null,
      "deltaPass": null,
      "obi": 0.129,
      "obiPass": true,
      "spreadBps": 7.1,
      "depthQuoteTopN": 474690,
      "liquidityTier": "LOW"
    },
    "rejectReasonCode": null,
    "volumeRatio": 1.39,
    "closedAt": 1776354368275
  },
  {
    "id": "1776357138500-TONUSDT",
    "symbol": "TONUSDT",
    "outcome": "LOSS",
    "regime": "HIGH_VOL_BREAKOUT",
    "btcRisk": "GREEN",
    "score": 80,
    "sector": "OTHER",
    "module": "VWAP_PULLBACK",
    "entryArchetype": "Institutional VWAP Reclaim",
    "liquidityTier": "LOW",
    "scoreBeforeMomentum": 80,
    "momentumAdjustment": 0,
    "requiredScore": 68,
    "requiredStrongCategories": null,
    "expectedHoldingHours": 12,
    "riskModel": {
      "tpMultiplier": 3,
      "slMultiplier": 1.4,
      "realRR": 2.14,
      "timeStopHours": 12
    },
    "hoursOpen": 0.5,
    "favorableMovePct": 0,
    "adverseMovePct": 0.91,
    "mfePct": 0,
    "maePct": 0.91,
    "entryMetrics": {
      "distToEma9": 0.29,
      "distToEma21": 0.83,
      "distToEma50": 1.27,
      "atrPercent": 0.52,
      "bbPercent": 0.83,
      "breakoutDistancePct": -0.69,
      "pullbackFromHigh20Pct": 0.69,
      "riskRewardRatio": 2.14,
      "timeStopHours": 12
    },
    "qualityBreakdown": {
      "trend": 100,
      "expansion": 0,
      "participation": 68.7,
      "execution": 63
    },
    "relativeStrengthSnapshot": {
      "rs1h": 0.0112,
      "rs4h": 0.0296,
      "rs24h": 0.04
    },
    "volumeLiquidityConfirmation": {
      "minVolumeRatio": 1.1,
      "volumeRatio": 1.43,
      "volumePass": true,
      "deltaRatio": null,
      "deltaPass": null,
      "obi": 0.054,
      "obiPass": true,
      "spreadBps": 7,
      "depthQuoteTopN": 672992,
      "liquidityTier": "LOW"
    },
    "rejectReasonCode": null,
    "volumeRatio": 1.43,
    "closedAt": 1776358903836
  },
  {
    "id": "1776355437470-SOLUSDT",
    "symbol": "SOLUSDT",
    "outcome": "LOSS",
    "regime": "HIGH_VOL_BREAKOUT",
    "btcRisk": "GREEN",
    "score": 87,
    "sector": "L1",
    "module": "VWAP_PULLBACK",
    "entryArchetype": "Institutional VWAP Reclaim",
    "liquidityTier": "ELITE",
    "scoreBeforeMomentum": 87,
    "momentumAdjustment": 0,
    "requiredScore": 68,
    "requiredStrongCategories": null,
    "expectedHoldingHours": 12,
    "riskModel": {
      "tpMultiplier": 3,
      "slMultiplier": 1.4,
      "realRR": 2.14,
      "timeStopHours": 12
    },
    "hoursOpen": 1.2,
    "favorableMovePct": 0,
    "adverseMovePct": 0.96,
    "mfePct": 0,
    "maePct": 0.96,
    "entryMetrics": {
      "distToEma9": 0.81,
      "distToEma21": 1.2,
      "distToEma50": 1.5,
      "atrPercent": 0.63,
      "bbPercent": 0.95,
      "breakoutDistancePct": -0.56,
      "pullbackFromHigh20Pct": 0.56,
      "riskRewardRatio": 2.14,
      "timeStopHours": 12
    },
    "qualityBreakdown": {
      "trend": 100,
      "expansion": 0,
      "participation": 67.2,
      "execution": 100
    },
    "relativeStrengthSnapshot": {
      "rs1h": 0.0132,
      "rs4h": 0.025,
      "rs24h": 0.02
    },
    "volumeLiquidityConfirmation": {
      "minVolumeRatio": 1.1,
      "volumeRatio": 1.36,
      "volumePass": true,
      "deltaRatio": null,
      "deltaPass": null,
      "obi": 0.128,
      "obiPass": true,
      "spreadBps": 1.2,
      "depthQuoteTopN": 2809958,
      "liquidityTier": "ELITE"
    },
    "rejectReasonCode": null,
    "volumeRatio": 1.36,
    "closedAt": 1776359736646
  },
  {
    "id": "1776354371560-ETHFIUSDT",
    "symbol": "ETHFIUSDT",
    "outcome": "WIN",
    "regime": "HIGH_VOL_BREAKOUT",
    "btcRisk": "GREEN",
    "score": 78,
    "sector": "OTHER",
    "module": "VWAP_PULLBACK",
    "entryArchetype": "Institutional VWAP Reclaim",
    "liquidityTier": "LOW",
    "scoreBeforeMomentum": 78,
    "momentumAdjustment": 0,
    "requiredScore": 68,
    "requiredStrongCategories": null,
    "expectedHoldingHours": 12,
    "riskModel": {
      "tpMultiplier": 3,
      "slMultiplier": 1.4,
      "realRR": 2.14,
      "timeStopHours": 12
    },
    "hoursOpen": 2.8,
    "favorableMovePct": 2.58,
    "adverseMovePct": 0,
    "mfePct": 2.58,
    "maePct": 0,
    "entryMetrics": {
      "distToEma9": 1.54,
      "distToEma21": 1.66,
      "distToEma50": 2,
      "atrPercent": 0.83,
      "bbPercent": 0.96,
      "breakoutDistancePct": -0.09,
      "pullbackFromHigh20Pct": 0.09,
      "riskRewardRatio": 2.14,
      "timeStopHours": 12
    },
    "qualityBreakdown": {
      "trend": 100,
      "expansion": 0,
      "participation": 62.5,
      "execution": 63
    },
    "relativeStrengthSnapshot": {
      "rs1h": 0.009,
      "rs4h": 0.0732,
      "rs24h": 0.05
    },
    "volumeLiquidityConfirmation": {
      "minVolumeRatio": 1.1,
      "volumeRatio": 1.13,
      "volumePass": true,
      "deltaRatio": null,
      "deltaPass": null,
      "obi": 0.311,
      "obiPass": true,
      "spreadBps": 4.2,
      "depthQuoteTopN": 307018,
      "liquidityTier": "LOW"
    },
    "rejectReasonCode": null,
    "volumeRatio": 1.13,
    "closedAt": 1776364283901
  },
  {
    "id": "1776354369592-BNBUSDT",
    "symbol": "BNBUSDT",
    "outcome": "WIN",
    "regime": "HIGH_VOL_BREAKOUT",
    "btcRisk": "GREEN",
    "score": 72,
    "sector": "BLUE_CHIP",
    "module": "VWAP_PULLBACK",
    "entryArchetype": "Institutional VWAP Reclaim",
    "liquidityTier": "MEDIUM",
    "scoreBeforeMomentum": 72,
    "momentumAdjustment": 0,
    "requiredScore": 71,
    "requiredStrongCategories": null,
    "expectedHoldingHours": 12,
    "riskModel": {
      "tpMultiplier": 2.85,
      "slMultiplier": 1.33,
      "realRR": 2.14,
      "timeStopHours": 12
    },
    "hoursOpen": 3,
    "favorableMovePct": 1.25,
    "adverseMovePct": 0.18,
    "mfePct": 1.25,
    "maePct": 0.18,
    "entryMetrics": {
      "distToEma9": 0.6,
      "distToEma21": 0.63,
      "distToEma50": 0.55,
      "atrPercent": 0.35,
      "bbPercent": 1.05,
      "breakoutDistancePct": 0.18,
      "pullbackFromHigh20Pct": -0.18,
      "riskRewardRatio": 2.14,
      "timeStopHours": 12
    },
    "qualityBreakdown": {
      "trend": 61.8,
      "expansion": 0,
      "participation": 83,
      "execution": 71
    },
    "relativeStrengthSnapshot": {
      "rs1h": 0.0029,
      "rs4h": 0.0059,
      "rs24h": 0
    },
    "volumeLiquidityConfirmation": {
      "minVolumeRatio": 1.1,
      "volumeRatio": 2.15,
      "volumePass": true,
      "deltaRatio": null,
      "deltaPass": null,
      "obi": -0.029,
      "obiPass": true,
      "spreadBps": 0.2,
      "depthQuoteTopN": 121316,
      "liquidityTier": "MEDIUM"
    },
    "rejectReasonCode": null,
    "volumeRatio": 2.15,
    "closedAt": 1776365154252
  },
  {
    "id": "1776355438076-DOGEUSDT",
    "symbol": "DOGEUSDT",
    "outcome": "WIN",
    "regime": "HIGH_VOL_BREAKOUT",
    "btcRisk": "GREEN",
    "score": 85,
    "sector": "MEME",
    "module": "VWAP_PULLBACK",
    "entryArchetype": "Institutional VWAP Reclaim",
    "liquidityTier": "HIGH",
    "scoreBeforeMomentum": 85,
    "momentumAdjustment": 0,
    "requiredScore": 68,
    "requiredStrongCategories": null,
    "expectedHoldingHours": 12,
    "riskModel": {
      "tpMultiplier": 3,
      "slMultiplier": 1.4,
      "realRR": 2.14,
      "timeStopHours": 12
    },
    "hoursOpen": 3.2,
    "favorableMovePct": 2.17,
    "adverseMovePct": 0.69,
    "mfePct": 2.17,
    "maePct": 0.69,
    "entryMetrics": {
      "distToEma9": 1,
      "distToEma21": 1.08,
      "distToEma50": 1.24,
      "atrPercent": 0.72,
      "bbPercent": 0.84,
      "breakoutDistancePct": -0.41,
      "pullbackFromHigh20Pct": 0.41,
      "riskRewardRatio": 2.14,
      "timeStopHours": 12
    },
    "qualityBreakdown": {
      "trend": 100,
      "expansion": 0,
      "participation": 69.7,
      "execution": 88
    },
    "relativeStrengthSnapshot": {
      "rs1h": 0.0108,
      "rs4h": 0.0417,
      "rs24h": 0.03
    },
    "volumeLiquidityConfirmation": {
      "minVolumeRatio": 1.1,
      "volumeRatio": 1.48,
      "volumePass": true,
      "deltaRatio": null,
      "deltaPass": null,
      "obi": 0.18,
      "obiPass": true,
      "spreadBps": 1,
      "depthQuoteTopN": 1389170,
      "liquidityTier": "HIGH"
    },
    "rejectReasonCode": null,
    "volumeRatio": 1.48,
    "closedAt": 1776366981395
  },
  {
    "id": "1776357912616-XRPUSDT",
    "symbol": "XRPUSDT",
    "outcome": "WIN",
    "regime": "HIGH_VOL_BREAKOUT",
    "btcRisk": "GREEN",
    "score": 87,
    "sector": "BLUE_CHIP",
    "module": "VWAP_PULLBACK",
    "entryArchetype": "Institutional VWAP Reclaim",
    "liquidityTier": "ELITE",
    "scoreBeforeMomentum": 87,
    "momentumAdjustment": 0,
    "requiredScore": 68,
    "requiredStrongCategories": null,
    "expectedHoldingHours": 12,
    "riskModel": {
      "tpMultiplier": 3,
      "slMultiplier": 1.4,
      "realRR": 2.14,
      "timeStopHours": 12
    },
    "hoursOpen": 3,
    "favorableMovePct": 2.73,
    "adverseMovePct": 0.54,
    "mfePct": 2.73,
    "maePct": 0.54,
    "entryMetrics": {
      "distToEma9": -0.03,
      "distToEma21": 0.32,
      "distToEma50": 0.8,
      "atrPercent": 0.7,
      "bbPercent": 0.63,
      "breakoutDistancePct": -1.28,
      "pullbackFromHigh20Pct": 1.28,
      "riskRewardRatio": 2.14,
      "timeStopHours": 12
    },
    "qualityBreakdown": {
      "trend": 100,
      "expansion": 0,
      "participation": 68.5,
      "execution": 100
    },
    "relativeStrengthSnapshot": {
      "rs1h": 0.0093,
      "rs4h": 0.0435,
      "rs24h": 0.03
    },
    "volumeLiquidityConfirmation": {
      "minVolumeRatio": 1.1,
      "volumeRatio": 1.42,
      "volumePass": true,
      "deltaRatio": null,
      "deltaPass": null,
      "obi": 0.038,
      "obiPass": true,
      "spreadBps": 0.7,
      "depthQuoteTopN": 856244,
      "liquidityTier": "ELITE"
    },
    "rejectReasonCode": null,
    "volumeRatio": 1.42,
    "closedAt": 1776368752310
  },
  {
    "id": "1776382300121-BNBUSDT",
    "symbol": "BNBUSDT",
    "outcome": "LOSS",
    "regime": "TRENDING",
    "btcRisk": "GREEN",
    "score": 73,
    "sector": "BLUE_CHIP",
    "module": "VWAP_PULLBACK",
    "entryArchetype": "Institutional VWAP Reclaim",
    "liquidityTier": "MEDIUM",
    "scoreBeforeMomentum": 73,
    "momentumAdjustment": 0,
    "requiredScore": 71,
    "requiredStrongCategories": null,
    "expectedHoldingHours": 12,
    "riskModel": {
      "tpMultiplier": 2.85,
      "slMultiplier": 1.33,
      "realRR": 2.14,
      "timeStopHours": 12
    },
    "hoursOpen": 2,
    "favorableMovePct": 0,
    "adverseMovePct": 0.62,
    "mfePct": 0,
    "maePct": 0.62,
    "entryMetrics": {
      "distToEma9": 0.25,
      "distToEma21": 0.44,
      "distToEma50": 0.98,
      "atrPercent": 0.29,
      "bbPercent": 0.72,
      "breakoutDistancePct": -0.28,
      "pullbackFromHigh20Pct": 0.28,
      "riskRewardRatio": 2.14,
      "timeStopHours": 12
    },
    "qualityBreakdown": {
      "trend": 83.8,
      "expansion": 0,
      "participation": 63.8,
      "execution": 71
    },
    "relativeStrengthSnapshot": {
      "rs1h": 0.0027,
      "rs4h": 0.0208,
      "rs24h": 0.02
    },
    "volumeLiquidityConfirmation": {
      "minVolumeRatio": 1.1,
      "volumeRatio": 1.19,
      "volumePass": true,
      "deltaRatio": null,
      "deltaPass": null,
      "obi": 0.468,
      "obiPass": true,
      "spreadBps": 0.2,
      "depthQuoteTopN": 142426,
      "liquidityTier": "MEDIUM"
    },
    "rejectReasonCode": null,
    "volumeRatio": 1.19,
    "closedAt": 1776389436997
  },
  {
    "id": "1776385898477-XRPUSDT",
    "symbol": "XRPUSDT",
    "outcome": "LOSS",
    "regime": "TRENDING",
    "btcRisk": "GREEN",
    "score": 86,
    "sector": "BLUE_CHIP",
    "module": "VWAP_PULLBACK",
    "entryArchetype": "Institutional VWAP Reclaim",
    "liquidityTier": "ELITE",
    "scoreBeforeMomentum": 86,
    "momentumAdjustment": 0,
    "requiredScore": 68,
    "requiredStrongCategories": null,
    "expectedHoldingHours": 12,
    "riskModel": {
      "tpMultiplier": 3,
      "slMultiplier": 1.4,
      "realRR": 2.14,
      "timeStopHours": 12
    },
    "hoursOpen": 1,
    "favorableMovePct": 0,
    "adverseMovePct": 0.73,
    "mfePct": 0,
    "maePct": 0.73,
    "entryMetrics": {
      "distToEma9": -0.34,
      "distToEma21": -0.21,
      "distToEma50": 0.51,
      "atrPercent": 0.49,
      "bbPercent": 0.13,
      "breakoutDistancePct": -1.48,
      "pullbackFromHigh20Pct": 1.48,
      "riskRewardRatio": 2.14,
      "timeStopHours": 12
    },
    "qualityBreakdown": {
      "trend": 100,
      "expansion": 0,
      "participation": 64.3,
      "execution": 100
    },
    "relativeStrengthSnapshot": {
      "rs1h": 0.0028,
      "rs4h": 0.0589,
      "rs24h": 0.03
    },
    "volumeLiquidityConfirmation": {
      "minVolumeRatio": 1.1,
      "volumeRatio": 1.21,
      "volumePass": true,
      "deltaRatio": null,
      "deltaPass": null,
      "obi": 0.157,
      "obiPass": true,
      "spreadBps": 0.7,
      "depthQuoteTopN": 802540,
      "liquidityTier": "ELITE"
    },
    "rejectReasonCode": null,
    "volumeRatio": 1.21,
    "closedAt": 1776389437124
  },
  {
    "id": "1776375124699-DOGEUSDT",
    "symbol": "DOGEUSDT",
    "outcome": "LOSS",
    "regime": "TRENDING",
    "btcRisk": "GREEN",
    "score": 97,
    "sector": "MEME",
    "module": "VWAP_PULLBACK",
    "entryArchetype": "Institutional VWAP Reclaim",
    "liquidityTier": "HIGH",
    "scoreBeforeMomentum": 97,
    "momentumAdjustment": 0,
    "requiredScore": 68,
    "requiredStrongCategories": null,
    "expectedHoldingHours": 12,
    "riskModel": {
      "tpMultiplier": 3,
      "slMultiplier": 1.4,
      "realRR": 2.14,
      "timeStopHours": 12
    },
    "hoursOpen": 5,
    "favorableMovePct": 0.14,
    "adverseMovePct": 1.18,
    "mfePct": 0.14,
    "maePct": 1.18,
    "entryMetrics": {
      "distToEma9": -0.08,
      "distToEma21": 0.3,
      "distToEma50": 1.13,
      "atrPercent": 0.71,
      "bbPercent": 0.57,
      "breakoutDistancePct": -1.28,
      "pullbackFromHigh20Pct": 1.28,
      "riskRewardRatio": 2.14,
      "timeStopHours": 12
    },
    "qualityBreakdown": {
      "trend": 100,
      "expansion": 0,
      "participation": 99.4,
      "execution": 85
    },
    "relativeStrengthSnapshot": {
      "rs1h": 0.0055,
      "rs4h": 0.0533,
      "rs24h": 0.04
    },
    "volumeLiquidityConfirmation": {
      "minVolumeRatio": 1.1,
      "volumeRatio": 2.97,
      "volumePass": true,
      "deltaRatio": null,
      "deltaPass": null,
      "obi": 0.488,
      "obiPass": true,
      "spreadBps": 3,
      "depthQuoteTopN": 942122,
      "liquidityTier": "HIGH"
    },
    "rejectReasonCode": null,
    "volumeRatio": 2.97,
    "closedAt": 1776393011143
  },
  {
    "id": "1776385902749-TRUMPUSDT",
    "symbol": "TRUMPUSDT",
    "outcome": "LOSS",
    "regime": "TRENDING",
    "btcRisk": "GREEN",
    "score": 87,
    "sector": "OTHER",
    "module": "VWAP_PULLBACK",
    "entryArchetype": "Institutional VWAP Reclaim",
    "liquidityTier": "LOW",
    "scoreBeforeMomentum": 87,
    "momentumAdjustment": 0,
    "requiredScore": 68,
    "requiredStrongCategories": null,
    "expectedHoldingHours": 12,
    "riskModel": {
      "tpMultiplier": 3,
      "slMultiplier": 1.4,
      "realRR": 2.14,
      "timeStopHours": 12
    },
    "hoursOpen": 2,
    "favorableMovePct": 0,
    "adverseMovePct": 1.95,
    "mfePct": 0,
    "maePct": 1.95,
    "entryMetrics": {
      "distToEma9": 0.41,
      "distToEma21": 0.79,
      "distToEma50": 1.98,
      "atrPercent": 0.76,
      "bbPercent": 0.74,
      "breakoutDistancePct": -1.35,
      "pullbackFromHigh20Pct": 1.35,
      "riskRewardRatio": 2.14,
      "timeStopHours": 12
    },
    "qualityBreakdown": {
      "trend": 100,
      "expansion": 0,
      "participation": 86.5,
      "execution": 63
    },
    "relativeStrengthSnapshot": {
      "rs1h": 0.0093,
      "rs4h": 0.0855,
      "rs24h": 0.01
    },
    "volumeLiquidityConfirmation": {
      "minVolumeRatio": 1.1,
      "volumeRatio": 2.32,
      "volumePass": true,
      "deltaRatio": null,
      "deltaPass": null,
      "obi": 0.304,
      "obiPass": true,
      "spreadBps": 3.2,
      "depthQuoteTopN": 367073,
      "liquidityTier": "LOW"
    },
    "rejectReasonCode": null,
    "volumeRatio": 2.32,
    "closedAt": 1776393011302
  },
  {
    "id": "1776388529791-TONUSDT",
    "symbol": "TONUSDT",
    "outcome": "LOSS",
    "regime": "HIGH_VOL_BREAKOUT",
    "btcRisk": "GREEN",
    "score": 86,
    "sector": "OTHER",
    "module": "VWAP_PULLBACK",
    "entryArchetype": "Institutional VWAP Reclaim",
    "liquidityTier": "LOW",
    "scoreBeforeMomentum": 86,
    "momentumAdjustment": 0,
    "requiredScore": 68,
    "requiredStrongCategories": null,
    "expectedHoldingHours": 12,
    "riskModel": {
      "tpMultiplier": 3,
      "slMultiplier": 1.4,
      "realRR": 2.14,
      "timeStopHours": 12
    },
    "hoursOpen": 1.2,
    "favorableMovePct": 0,
    "adverseMovePct": 1.6,
    "mfePct": 0,
    "maePct": 1.6,
    "entryMetrics": {
      "distToEma9": 0.06,
      "distToEma21": 0.63,
      "distToEma50": 1.24,
      "atrPercent": 0.51,
      "bbPercent": 0.76,
      "breakoutDistancePct": -0.89,
      "pullbackFromHigh20Pct": 0.89,
      "riskRewardRatio": 2.14,
      "timeStopHours": 12
    },
    "qualityBreakdown": {
      "trend": 100,
      "expansion": 0,
      "participation": 82.3,
      "execution": 63
    },
    "relativeStrengthSnapshot": {
      "rs1h": 0.0228,
      "rs4h": 0.0268,
      "rs24h": 0.03
    },
    "volumeLiquidityConfirmation": {
      "minVolumeRatio": 1.1,
      "volumeRatio": 2.12,
      "volumePass": true,
      "deltaRatio": null,
      "deltaPass": null,
      "obi": 0.126,
      "obiPass": true,
      "spreadBps": 6.9,
      "depthQuoteTopN": 607348,
      "liquidityTier": "LOW"
    },
    "rejectReasonCode": null,
    "volumeRatio": 2.12,
    "closedAt": 1776393011437
  },
  {
    "id": "1776391280563-LTCUSDT",
    "symbol": "LTCUSDT",
    "outcome": "LOSS",
    "regime": "TRENDING",
    "btcRisk": "GREEN",
    "score": 79,
    "sector": "OTHER",
    "module": "VWAP_PULLBACK",
    "entryArchetype": "Institutional VWAP Reclaim",
    "liquidityTier": "LOW",
    "scoreBeforeMomentum": 79,
    "momentumAdjustment": 0,
    "requiredScore": 68,
    "requiredStrongCategories": null,
    "expectedHoldingHours": 12,
    "riskModel": {
      "tpMultiplier": 3,
      "slMultiplier": 1.4,
      "realRR": 2.14,
      "timeStopHours": 12
    },
    "hoursOpen": 0.5,
    "favorableMovePct": 0,
    "adverseMovePct": 0.57,
    "mfePct": 0,
    "maePct": 0.57,
    "entryMetrics": {
      "distToEma9": -0.14,
      "distToEma21": -0.18,
      "distToEma50": 0.07,
      "atrPercent": 0.34,
      "bbPercent": 0.27,
      "breakoutDistancePct": -0.85,
      "pullbackFromHigh20Pct": 0.85,
      "riskRewardRatio": 2.14,
      "timeStopHours": 12
    },
    "qualityBreakdown": {
      "trend": 100,
      "expansion": 0,
      "participation": 65,
      "execution": 66
    },
    "relativeStrengthSnapshot": {
      "rs1h": 0.0046,
      "rs4h": 0.0317,
      "rs24h": 0.02
    },
    "volumeLiquidityConfirmation": {
      "minVolumeRatio": 1.1,
      "volumeRatio": 1.25,
      "volumePass": true,
      "deltaRatio": null,
      "deltaPass": null,
      "obi": 0.121,
      "obiPass": true,
      "spreadBps": 1.8,
      "depthQuoteTopN": 625553,
      "liquidityTier": "LOW"
    },
    "rejectReasonCode": null,
    "volumeRatio": 1.25,
    "closedAt": 1776393011554
  },
  {
    "id": "1776397553339-ETHFIUSDT",
    "symbol": "ETHFIUSDT",
    "outcome": "LOSS",
    "regime": "TRENDING",
    "btcRisk": "GREEN",
    "score": 79,
    "sector": "OTHER",
    "module": "VWAP_PULLBACK",
    "entryArchetype": "Institutional VWAP Reclaim",
    "liquidityTier": "LOW",
    "scoreBeforeMomentum": 79,
    "momentumAdjustment": 0,
    "requiredScore": 68,
    "requiredStrongCategories": null,
    "expectedHoldingHours": 12,
    "riskModel": {
      "tpMultiplier": 3,
      "slMultiplier": 1.4,
      "realRR": 2.14,
      "timeStopHours": 12
    },
    "hoursOpen": 1.5,
    "favorableMovePct": 0,
    "adverseMovePct": 1.27,
    "mfePct": 0,
    "maePct": 1.27,
    "entryMetrics": {
      "distToEma9": 0.26,
      "distToEma21": 0.22,
      "distToEma50": 0.74,
      "atrPercent": 0.6,
      "bbPercent": 0.65,
      "breakoutDistancePct": -0.78,
      "pullbackFromHigh20Pct": 0.78,
      "riskRewardRatio": 2.14,
      "timeStopHours": 12
    },
    "qualityBreakdown": {
      "trend": 100,
      "expansion": 0,
      "participation": 66.3,
      "execution": 63
    },
    "relativeStrengthSnapshot": {
      "rs1h": 0.0031,
      "rs4h": 0.1242,
      "rs24h": 0.05
    },
    "volumeLiquidityConfirmation": {
      "minVolumeRatio": 1.1,
      "volumeRatio": 1.32,
      "volumePass": true,
      "deltaRatio": null,
      "deltaPass": null,
      "obi": 0.151,
      "obiPass": true,
      "spreadBps": 6.2,
      "depthQuoteTopN": 361249,
      "liquidityTier": "LOW"
    },
    "rejectReasonCode": null,
    "volumeRatio": 1.32,
    "closedAt": 1776402956739
  },
  {
    "id": "1776413099031-FILUSDT",
    "symbol": "FILUSDT",
    "outcome": "LOSS",
    "regime": "TRENDING",
    "btcRisk": "GREEN",
    "score": 92,
    "sector": "OTHER",
    "module": "VWAP_PULLBACK",
    "entryArchetype": "Institutional VWAP Reclaim",
    "liquidityTier": "LOW",
    "scoreBeforeMomentum": 92,
    "momentumAdjustment": 0,
    "requiredScore": 68,
    "requiredStrongCategories": null,
    "expectedHoldingHours": 12,
    "riskModel": {
      "tpMultiplier": 3,
      "slMultiplier": 1.4,
      "realRR": 2.14,
      "timeStopHours": 12
    },
    "hoursOpen": 0.4,
    "favorableMovePct": 0,
    "adverseMovePct": 1.65,
    "mfePct": 0,
    "maePct": 1.65,
    "entryMetrics": {
      "distToEma9": 1.58,
      "distToEma21": 2.07,
      "distToEma50": 2.1,
      "atrPercent": 0.68,
      "bbPercent": 1.18,
      "breakoutDistancePct": 0.49,
      "pullbackFromHigh20Pct": -0.49,
      "riskRewardRatio": 2.14,
      "timeStopHours": 12
    },
    "qualityBreakdown": {
      "trend": 100,
      "expansion": 0,
      "participation": 98.7,
      "execution": 63
    },
    "relativeStrengthSnapshot": {
      "rs1h": 0.0214,
      "rs4h": 0.0978,
      "rs24h": 0.02
    },
    "volumeLiquidityConfirmation": {
      "minVolumeRatio": 1.1,
      "volumeRatio": 2.94,
      "volumePass": true,
      "deltaRatio": null,
      "deltaPass": null,
      "obi": 0.138,
      "obiPass": true,
      "spreadBps": 4,
      "depthQuoteTopN": 584642,
      "liquidityTier": "LOW"
    },
    "rejectReasonCode": null,
    "volumeRatio": 2.94,
    "closedAt": 1776414695422
  },
  {
    "id": "1776413099649-TONUSDT",
    "symbol": "TONUSDT",
    "outcome": "LOSS",
    "regime": "TRENDING",
    "btcRisk": "GREEN",
    "score": 93,
    "sector": "OTHER",
    "module": "VWAP_PULLBACK",
    "entryArchetype": "Institutional VWAP Reclaim",
    "liquidityTier": "LOW",
    "scoreBeforeMomentum": 93,
    "momentumAdjustment": 0,
    "requiredScore": 68,
    "requiredStrongCategories": null,
    "expectedHoldingHours": 12,
    "riskModel": {
      "tpMultiplier": 3,
      "slMultiplier": 1.4,
      "realRR": 2.14,
      "timeStopHours": 12
    },
    "hoursOpen": 0.7,
    "favorableMovePct": 0,
    "adverseMovePct": 0.9,
    "mfePct": 0,
    "maePct": 0.9,
    "entryMetrics": {
      "distToEma9": 0.77,
      "distToEma21": 1.02,
      "distToEma50": 1.35,
      "atrPercent": 0.5,
      "bbPercent": 1.11,
      "breakoutDistancePct": 0.28,
      "pullbackFromHigh20Pct": -0.28,
      "riskRewardRatio": 2.14,
      "timeStopHours": 12
    },
    "qualityBreakdown": {
      "trend": 100,
      "expansion": 0,
      "participation": 100,
      "execution": 63
    },
    "relativeStrengthSnapshot": {
      "rs1h": 0.0162,
      "rs4h": 0.0498,
      "rs24h": 0.03
    },
    "volumeLiquidityConfirmation": {
      "minVolumeRatio": 1.1,
      "volumeRatio": 8.93,
      "volumePass": true,
      "deltaRatio": null,
      "deltaPass": null,
      "obi": 0.076,
      "obiPass": true,
      "spreadBps": 6.9,
      "depthQuoteTopN": 647864,
      "liquidityTier": "LOW"
    },
    "rejectReasonCode": null,
    "volumeRatio": 8.93,
    "closedAt": 1776415528116
  },
  {
    "id": "1776415529762-XRPUSDT",
    "symbol": "XRPUSDT",
    "outcome": "LOSS",
    "regime": "TRENDING",
    "btcRisk": "GREEN",
    "score": 90,
    "sector": "BLUE_CHIP",
    "module": "VWAP_PULLBACK",
    "entryArchetype": "Institutional VWAP Reclaim",
    "liquidityTier": "ELITE",
    "scoreBeforeMomentum": 90,
    "momentumAdjustment": 0,
    "requiredScore": 68,
    "requiredStrongCategories": null,
    "expectedHoldingHours": 12,
    "riskModel": {
      "tpMultiplier": 3,
      "slMultiplier": 1.4,
      "realRR": 2.14,
      "timeStopHours": 12
    },
    "hoursOpen": 1.8,
    "favorableMovePct": 0,
    "adverseMovePct": 0.49,
    "mfePct": 0,
    "maePct": 0.49,
    "entryMetrics": {
      "distToEma9": 0.35,
      "distToEma21": 0.49,
      "distToEma50": 0.54,
      "atrPercent": 0.34,
      "bbPercent": 1.02,
      "breakoutDistancePct": 0.06,
      "pullbackFromHigh20Pct": -0.06,
      "riskRewardRatio": 2.14,
      "timeStopHours": 12
    },
    "qualityBreakdown": {
      "trend": 100,
      "expansion": 0,
      "participation": 77,
      "execution": 98
    },
    "relativeStrengthSnapshot": {
      "rs1h": 0.0005,
      "rs4h": 0.0429,
      "rs24h": 0.02
    },
    "volumeLiquidityConfirmation": {
      "minVolumeRatio": 1.1,
      "volumeRatio": 1.85,
      "volumePass": true,
      "deltaRatio": null,
      "deltaPass": null,
      "obi": 0.041,
      "obiPass": true,
      "spreadBps": 2.1,
      "depthQuoteTopN": 982821,
      "liquidityTier": "ELITE"
    },
    "rejectReasonCode": null,
    "volumeRatio": 1.85,
    "closedAt": 1776421872110
  },
  {
    "id": "1776420171061-ETHFIUSDT",
    "symbol": "ETHFIUSDT",
    "outcome": "LOSS",
    "regime": "TRENDING",
    "btcRisk": "GREEN",
    "score": 79,
    "sector": "OTHER",
    "module": "VWAP_PULLBACK",
    "entryArchetype": "Institutional VWAP Reclaim",
    "liquidityTier": "LOW",
    "scoreBeforeMomentum": 79,
    "momentumAdjustment": 0,
    "requiredScore": 68,
    "requiredStrongCategories": null,
    "expectedHoldingHours": 12,
    "riskModel": {
      "tpMultiplier": 3,
      "slMultiplier": 1.4,
      "realRR": 2.14,
      "timeStopHours": 12
    },
    "hoursOpen": 0.5,
    "favorableMovePct": 0,
    "adverseMovePct": 1.05,
    "mfePct": 0,
    "maePct": 1.05,
    "entryMetrics": {
      "distToEma9": 0.79,
      "distToEma21": 1.21,
      "distToEma50": 1.58,
      "atrPercent": 0.55,
      "bbPercent": 1,
      "breakoutDistancePct": 0.19,
      "pullbackFromHigh20Pct": -0.19,
      "riskRewardRatio": 2.14,
      "timeStopHours": 12
    },
    "qualityBreakdown": {
      "trend": 100,
      "expansion": 0,
      "participation": 65,
      "execution": 63
    },
    "relativeStrengthSnapshot": {
      "rs1h": 0.0025,
      "rs4h": 0.1055,
      "rs24h": 0.05
    },
    "volumeLiquidityConfirmation": {
      "minVolumeRatio": 1.1,
      "volumeRatio": 1.25,
      "volumePass": true,
      "deltaRatio": null,
      "deltaPass": null,
      "obi": 0.121,
      "obiPass": true,
      "spreadBps": 6.2,
      "depthQuoteTopN": 261871,
      "liquidityTier": "LOW"
    },
    "rejectReasonCode": null,
    "volumeRatio": 1.25,
    "closedAt": 1776421872233
  },
  {
    "id": "1776420171497-ADAUSDT",
    "symbol": "ADAUSDT",
    "outcome": "LOSS",
    "regime": "TRENDING",
    "btcRisk": "GREEN",
    "score": 80,
    "sector": "L1",
    "module": "VWAP_PULLBACK",
    "entryArchetype": "Institutional VWAP Reclaim",
    "liquidityTier": "MEDIUM",
    "scoreBeforeMomentum": 80,
    "momentumAdjustment": 0,
    "requiredScore": 71,
    "requiredStrongCategories": null,
    "expectedHoldingHours": 12,
    "riskModel": {
      "tpMultiplier": 2.85,
      "slMultiplier": 1.33,
      "realRR": 2.14,
      "timeStopHours": 12
    },
    "hoursOpen": 0.5,
    "favorableMovePct": 0,
    "adverseMovePct": 1.12,
    "mfePct": 0,
    "maePct": 1.12,
    "entryMetrics": {
      "distToEma9": 0.36,
      "distToEma21": 0.75,
      "distToEma50": 1,
      "atrPercent": 0.55,
      "bbPercent": 0.84,
      "breakoutDistancePct": -0.62,
      "pullbackFromHigh20Pct": 0.62,
      "riskRewardRatio": 2.14,
      "timeStopHours": 12
    },
    "qualityBreakdown": {
      "trend": 100,
      "expansion": 0,
      "participation": 63.9,
      "execution": 71
    },
    "relativeStrengthSnapshot": {
      "rs1h": 0.0037,
      "rs4h": 0.0492,
      "rs24h": 0.02
    },
    "volumeLiquidityConfirmation": {
      "minVolumeRatio": 1.1,
      "volumeRatio": 1.2,
      "volumePass": true,
      "deltaRatio": null,
      "deltaPass": null,
      "obi": -0.011,
      "obiPass": true,
      "spreadBps": 3.9,
      "depthQuoteTopN": 1695362,
      "liquidityTier": "MEDIUM"
    },
    "rejectReasonCode": null,
    "volumeRatio": 1.2,
    "closedAt": 1776421872352
  },
  {
    "id": "1776423795486-LTCUSDT",
    "symbol": "LTCUSDT",
    "outcome": "WIN",
    "regime": "TRENDING",
    "btcRisk": "GREEN",
    "score": 69,
    "sector": "OTHER",
    "module": "VWAP_PULLBACK",
    "entryArchetype": "Institutional VWAP Reclaim",
    "liquidityTier": "LOW",
    "scoreBeforeMomentum": 69,
    "momentumAdjustment": 0,
    "requiredScore": 68,
    "requiredStrongCategories": null,
    "expectedHoldingHours": 12,
    "riskModel": {
      "tpMultiplier": 3,
      "slMultiplier": 1.4,
      "realRR": 2.14,
      "timeStopHours": 12
    },
    "hoursOpen": 2,
    "favorableMovePct": 1.14,
    "adverseMovePct": 0,
    "mfePct": 1.14,
    "maePct": 0,
    "entryMetrics": {
      "distToEma9": -0.06,
      "distToEma21": 0.02,
      "distToEma50": 0.13,
      "atrPercent": 0.33,
      "bbPercent": 0.51,
      "breakoutDistancePct": -0.78,
      "pullbackFromHigh20Pct": 0.78,
      "riskRewardRatio": 2.14,
      "timeStopHours": 12
    },
    "qualityBreakdown": {
      "trend": 74.2,
      "expansion": 0,
      "participation": 66.5,
      "execution": 66
    },
    "relativeStrengthSnapshot": {
      "rs1h": 0.0013,
      "rs4h": 0.0153,
      "rs24h": 0
    },
    "volumeLiquidityConfirmation": {
      "minVolumeRatio": 1.1,
      "volumeRatio": 1.32,
      "volumePass": true,
      "deltaRatio": null,
      "deltaPass": null,
      "obi": 0.183,
      "obiPass": true,
      "spreadBps": 1.8,
      "depthQuoteTopN": 653952,
      "liquidityTier": "LOW"
    },
    "rejectReasonCode": null,
    "volumeRatio": 1.32,
    "closedAt": 1776430889020
  },
  {
    "id": "1776425419619-SHIBUSDT",
    "symbol": "SHIBUSDT",
    "outcome": "WIN",
    "regime": "TRENDING",
    "btcRisk": "GREEN",
    "score": 79,
    "sector": "MEME",
    "module": "VWAP_PULLBACK",
    "entryArchetype": "Institutional VWAP Reclaim",
    "liquidityTier": "LOW",
    "scoreBeforeMomentum": 79,
    "momentumAdjustment": 0,
    "requiredScore": 68,
    "requiredStrongCategories": null,
    "expectedHoldingHours": 12,
    "riskModel": {
      "tpMultiplier": 3,
      "slMultiplier": 1.4,
      "realRR": 2.14,
      "timeStopHours": 12
    },
    "hoursOpen": 1.8,
    "favorableMovePct": 2.1,
    "adverseMovePct": 0,
    "mfePct": 2.1,
    "maePct": 0,
    "entryMetrics": {
      "distToEma9": 0.64,
      "distToEma21": 0.85,
      "distToEma50": 0.93,
      "atrPercent": 0.51,
      "bbPercent": 0.93,
      "breakoutDistancePct": -0.24,
      "pullbackFromHigh20Pct": 0.24,
      "riskRewardRatio": 2.14,
      "timeStopHours": 12
    },
    "qualityBreakdown": {
      "trend": 100,
      "expansion": 0,
      "participation": 67,
      "execution": 63
    },
    "relativeStrengthSnapshot": {
      "rs1h": 0.006,
      "rs4h": 0.0365,
      "rs24h": 0.02
    },
    "volumeLiquidityConfirmation": {
      "minVolumeRatio": 1.1,
      "volumeRatio": 1.35,
      "volumePass": true,
      "deltaRatio": null,
      "deltaPass": null,
      "obi": 0.298,
      "obiPass": true,
      "spreadBps": 6.4,
      "depthQuoteTopN": 474724,
      "liquidityTier": "LOW"
    },
    "rejectReasonCode": null,
    "volumeRatio": 1.35,
    "closedAt": 1776431736582
  },
  {
    "id": "1776428199445-BONKUSDT",
    "symbol": "BONKUSDT",
    "outcome": "WIN",
    "regime": "TRENDING",
    "btcRisk": "GREEN",
    "score": 81,
    "sector": "OTHER",
    "module": "VWAP_PULLBACK",
    "entryArchetype": "Institutional VWAP Reclaim",
    "liquidityTier": "LOW",
    "scoreBeforeMomentum": 81,
    "momentumAdjustment": 0,
    "requiredScore": 68,
    "requiredStrongCategories": null,
    "expectedHoldingHours": 12,
    "riskModel": {
      "tpMultiplier": 3,
      "slMultiplier": 1.4,
      "realRR": 2.14,
      "timeStopHours": 12
    },
    "hoursOpen": 1,
    "favorableMovePct": 2.29,
    "adverseMovePct": 0,
    "mfePct": 2.29,
    "maePct": 0,
    "entryMetrics": {
      "distToEma9": 0.61,
      "distToEma21": 0.77,
      "distToEma50": 0.7,
      "atrPercent": 0.69,
      "bbPercent": 0.85,
      "breakoutDistancePct": -0.45,
      "pullbackFromHigh20Pct": 0.45,
      "riskRewardRatio": 2.14,
      "timeStopHours": 12
    },
    "qualityBreakdown": {
      "trend": 100,
      "expansion": 0,
      "participation": 70.2,
      "execution": 66
    },
    "relativeStrengthSnapshot": {
      "rs1h": 0.002,
      "rs4h": 0.0432,
      "rs24h": 0.03
    },
    "volumeLiquidityConfirmation": {
      "minVolumeRatio": 1.1,
      "volumeRatio": 1.51,
      "volumePass": true,
      "deltaRatio": null,
      "deltaPass": null,
      "obi": 0.095,
      "obiPass": true,
      "spreadBps": 1.6,
      "depthQuoteTopN": 367402,
      "liquidityTier": "LOW"
    },
    "rejectReasonCode": null,
    "volumeRatio": 1.51,
    "closedAt": 1776431736722
  },
  {
    "id": "1776348180847-INJUSDT",
    "symbol": "INJUSDT",
    "outcome": "WIN",
    "regime": "HIGH_VOL_BREAKOUT",
    "btcRisk": "GREEN",
    "score": 93,
    "sector": "OTHER",
    "module": "VWAP_PULLBACK",
    "entryArchetype": "Institutional VWAP Reclaim",
    "liquidityTier": "LOW",
    "scoreBeforeMomentum": 93,
    "momentumAdjustment": 0,
    "requiredScore": 68,
    "requiredStrongCategories": null,
    "expectedHoldingHours": 12,
    "riskModel": {
      "tpMultiplier": 3,
      "slMultiplier": 1.4,
      "realRR": 2.14,
      "timeStopHours": 12
    },
    "hoursOpen": 23.7,
    "favorableMovePct": 3.44,
    "adverseMovePct": 0.66,
    "mfePct": 3.44,
    "maePct": 0.66,
    "entryMetrics": {
      "distToEma9": -0.95,
      "distToEma21": -0.35,
      "distToEma50": 0.65,
      "atrPercent": 1.13,
      "bbPercent": 0.48,
      "breakoutDistancePct": -3.54,
      "pullbackFromHigh20Pct": 3.54,
      "riskRewardRatio": 2.14,
      "timeStopHours": 12
    },
    "qualityBreakdown": {
      "trend": 100,
      "expansion": 0,
      "participation": 100,
      "execution": 63
    },
    "relativeStrengthSnapshot": {
      "rs1h": 0.0143,
      "rs4h": 0.1131,
      "rs24h": 0.09
    },
    "volumeLiquidityConfirmation": {
      "minVolumeRatio": 1.1,
      "volumeRatio": 3.38,
      "volumePass": true,
      "deltaRatio": null,
      "deltaPass": null,
      "obi": 0.16,
      "obiPass": true,
      "spreadBps": 6,
      "depthQuoteTopN": 279700,
      "liquidityTier": "LOW"
    },
    "rejectReasonCode": null,
    "volumeRatio": 3.38,
    "closedAt": 1776433518832
  }
]